{
  "products": [
    {
      "id": "",
      "transaction_details": "",
      "spend_category": "Medical",
      "amount": 20,
      "date": "10/05/2018",
      "paymentType": "make payment"
    },
    {
      "transaction_details": "llllll",
      "id": "roKK6On"
    },
    {
      "transaction_details": "ssss",
      "id": "TzPUdMk"
    },
    {
      "transaction_details": "tttt",
      "id": "gHu-JpB"
    },
    {
      "transaction_details": "gggg",
      "id": "YqKy-wI"
    },
    {
      "transaction_details": "fgfdg",
      "id": "pFCj17j"
    },
    {
      "transaction_details": "wwww",
      "id": "D1plnSx"
    },
    {
      "transaction_details": "ssss",
      "id": "OCzfn4d"
    },
    {
      "transaction_details": "wwwww",
      "id": "VfNWpwl"
    },
    {
      "transaction_details": "wwwww",
      "id": "aio_KNq"
    },
    {
      "transaction_details": "aaaaaa",
      "id": "2gGUhyx"
    },
    {
      "transaction_details": "zzzz",
      "id": "X1jADPW"
    },
    {
      "transaction_details": "ccccc",
      "id": "HvrZmPs"
    },
    {
      "transaction_details": "ddd",
      "id": "x4jQbR5"
    },
    {
      "transaction_details": "sssss",
      "id": "Aisqpkv"
    },
    {
      "transaction_details": "gf",
      "id": "yNR0qoZ"
    },
    {
      "transaction_details": "rhrg",
      "id": "KJ8zUiS"
    },
    {
      "transaction_details": "fgg",
      "amount": "444",
      "date": "ffff",
      "id": "e7jlhMa"
    },
    {
      "transaction_details": "ssss",
      "amount": "",
      "date": "",
      "id": "8_yhdAc"
    },
    {
      "transaction_details": "",
      "amount": "444",
      "date": "eee",
      "id": "BXkBmC2"
    },
    {
      "transaction_details": "zxxzz",
      "amount": "111",
      "date": "eee",
      "id": "enVzeqB"
    },
    {
      "transaction_details": "",
      "amount": "",
      "date": "",
      "id": "9m7GoJJ"
    },
    {
      "transaction_details": "",
      "amount": "",
      "date": "",
      "id": "babOAuc"
    },
    {
      "transaction_details": "",
      "amount": "",
      "date": "",
      "id": "hOjGcC7"
    },
    {
      "transaction_details": "",
      "amount": "",
      "date": "",
      "id": "EZKRwyi"
    },
    {
      "transaction_details": "",
      "amount": "",
      "date": "",
      "id": "gEQrtUs"
    },
    {
      "transaction_details": "",
      "amount": "",
      "date": "",
      "id": "5O8YE3s"
    },
    {
      "transaction_details": "",
      "amount": "",
      "date": "",
      "id": "fdxu-_p"
    },
    {
      "transaction_details": "WWW",
      "amount": "222",
      "date": "12/12/2019",
      "id": "5kLnCCY"
    },
    {
      "transaction_details": "",
      "amount": "",
      "date": "",
      "id": "NaoCYyC"
    },
    {
      "transaction_details": "",
      "amount": "",
      "date": "",
      "id": "NvqikqG"
    },
    {
      "transaction_details": "",
      "amount": "",
      "date": "",
      "id": "xKnVgRV"
    },
    {
      "transaction_details": "",
      "amount": "",
      "date": "",
      "id": "uCkwutA"
    },
    {
      "transaction_details": "",
      "amount": "",
      "date": "",
      "id": "pQvbep_"
    },
    {
      "transaction_details": "",
      "amount": "",
      "date": "",
      "id": "MCJEpsE"
    },
    {
      "transaction_details": "",
      "amount": "",
      "date": "",
      "id": "nkCOldW"
    },
    {
      "transaction_details": "",
      "amount": "",
      "date": "",
      "id": "zv6g30C"
    },
    {
      "transaction_details": "",
      "amount": "",
      "date": "",
      "id": "9G_fYev"
    },
    {
      "transaction_details": "",
      "amount": "",
      "date": "",
      "id": "JxG4o8Y"
    },
    {
      "transaction_details": "",
      "amount": "",
      "date": "",
      "id": "QAnlAK6"
    }
  ]
}